{"dist":"URI-1.76","target":"URI::Escape","name":"URI","version":"1.76","provides":{"URI::data":{"version":"1.76","file":"lib/URI/data.pm"},"URI::telnet":{"file":"lib/URI/telnet.pm","version":"1.76"},"URI::gopher":{"version":"1.76","file":"lib/URI/gopher.pm"},"URI::rlogin":{"file":"lib/URI/rlogin.pm","version":"1.76"},"URI::sips":{"version":"1.76","file":"lib/URI/sips.pm"},"URI::Heuristic":{"version":"4.20","file":"lib/URI/Heuristic.pm"},"URI::ldaps":{"version":"1.76","file":"lib/URI/ldaps.pm"},"URI::http":{"version":"1.76","file":"lib/URI/http.pm"},"URI::rtspu":{"version":"1.76","file":"lib/URI/rtspu.pm"},"URI::file::QNX":{"version":"1.76","file":"lib/URI/file/QNX.pm"},"URI::ftp":{"version":"1.76","file":"lib/URI/ftp.pm"},"URI::ldap":{"file":"lib/URI/ldap.pm","version":"1.76"},"URI::https":{"version":"1.76","file":"lib/URI/https.pm"},"URI::file::Win32":{"version":"1.76","file":"lib/URI/file/Win32.pm"},"URI::file::OS2":{"file":"lib/URI/file/OS2.pm","version":"1.76"},"URI::URL":{"version":"5.04","file":"lib/URI/URL.pm"},"URI::QueryParam":{"file":"lib/URI/QueryParam.pm","version":"1.76"},"URI":{"file":"lib/URI.pm","version":"1.76"},"URI::ldapi":{"file":"lib/URI/ldapi.pm","version":"1.76"},"URI::IRI":{"file":"lib/URI/IRI.pm","version":"1.76"},"URI::snews":{"version":"1.76","file":"lib/URI/snews.pm"},"URI::pop":{"file":"lib/URI/pop.pm","version":"1.76"},"URI::file::Unix":{"version":"1.76","file":"lib/URI/file/Unix.pm"},"URI::file":{"file":"lib/URI/file.pm","version":"4.21"},"URI::urn::isbn":{"version":"1.76","file":"lib/URI/urn/isbn.pm"},"URI::file::FAT":{"version":"1.76","file":"lib/URI/file/FAT.pm"},"URI::mms":{"version":"1.76","file":"lib/URI/mms.pm"},"URI::Escape":{"file":"lib/URI/Escape.pm","version":"3.31"},"URI::sftp":{"file":"lib/URI/sftp.pm","version":"1.76"},"URI::tn3270":{"file":"lib/URI/tn3270.pm","version":"1.76"},"URI::WithBase":{"version":"2.20","file":"lib/URI/WithBase.pm"},"URI::news":{"version":"1.76","file":"lib/URI/news.pm"},"URI::sip":{"version":"1.76","file":"lib/URI/sip.pm"},"URI::file::Mac":{"file":"lib/URI/file/Mac.pm","version":"1.76"},"URI::rtsp":{"version":"1.76","file":"lib/URI/rtsp.pm"},"URI::urn::oid":{"file":"lib/URI/urn/oid.pm","version":"1.76"},"URI::urn":{"file":"lib/URI/urn.pm","version":"1.76"},"URI::Split":{"file":"lib/URI/Split.pm","version":"1.76"},"URI::rsync":{"version":"1.76","file":"lib/URI/rsync.pm"},"URI::file::Base":{"version":"1.76","file":"lib/URI/file/Base.pm"},"URI::ssh":{"version":"1.76","file":"lib/URI/ssh.pm"},"URI::nntp":{"version":"1.76","file":"lib/URI/nntp.pm"},"URI::mailto":{"file":"lib/URI/mailto.pm","version":"1.76"}},"pathname":"O/OA/OALDERS/URI-1.76.tar.gz"}