{"version":"2.010","dist":"Log-Dispatchouli-2.010","provides":{"DDR::Parent":{"file":"t/lib/DDR/Parent.pm"},"Log::Dispatchouli::Global":{"file":"lib/Log/Dispatchouli/Global.pm","version":"2.010"},"SDR::Parent":{"file":"t/lib/SDR/Parent.pm"},"Log::Dispatchouli::Proxy":{"file":"lib/Log/Dispatchouli/Proxy.pm","version":"2.010"},"Log::Dispatchouli":{"file":"lib/Log/Dispatchouli.pm","version":"2.010"},"SDR::Child":{"file":"t/lib/SDR/Child.pm"},"DDR::Child":{"file":"t/lib/DDR/Child.pm"}},"pathname":"R/RJ/RJBS/Log-Dispatchouli-2.010.tar.gz","name":"Log::Dispatchouli","target":"Log::Dispatchouli"}