{"target":"Encode","dist":"Encode-3.02","provides":{"Encode::UTF_EBCDIC":{"version":"3.02","file":"Encode.pm"},"Encode::CN::HZ":{"version":"2.10","file":"lib/Encode/CN/HZ.pm"},"Encode::GSM0338":{"version":"2.07","file":"lib/Encode/GSM0338.pm"},"Encode::TW":{"file":"TW/TW.pm","version":"2.03"},"Encode::EBCDIC":{"file":"EBCDIC/EBCDIC.pm","version":"2.02"},"Encode::Byte":{"file":"Byte/Byte.pm","version":"2.04"},"Encode::KR":{"file":"KR/KR.pm","version":"2.03"},"Encode::KR::2022_KR":{"file":"lib/Encode/KR/2022_KR.pm","version":"2.04"},"Encode::Internal":{"version":"3.02","file":"Encode.pm"},"Encode::CN":{"file":"CN/CN.pm","version":"2.03"},"Encode::Symbol":{"file":"Symbol/Symbol.pm","version":"2.02"},"Encode::MIME::Header::ISO_2022_JP":{"file":"lib/Encode/MIME/Header/ISO_2022_JP.pm","version":"1.09"},"Encode":{"file":"Encode.pm","version":"3.02"},"Encode::JP::JIS7":{"file":"lib/Encode/JP/JIS7.pm","version":"2.08"},"Encode::JP":{"file":"JP/JP.pm","version":"2.04"},"Encode::Encoding":{"file":"lib/Encode/Encoding.pm","version":"2.08"},"Encode::Alias":{"file":"lib/Encode/Alias.pm","version":"2.24"},"Encode::Guess":{"file":"lib/Encode/Guess.pm","version":"2.07"},"Encode::XS":{"version":"3.02","file":"Encode.pm"},"Encode::MIME::Header":{"version":"2.28","file":"lib/Encode/MIME/Header.pm"},"Encode::Encoder":{"version":"2.03","file":"lib/Encode/Encoder.pm"},"Encode::JP::H2Z":{"file":"lib/Encode/JP/H2Z.pm","version":"2.02"},"Encode::MIME::Name":{"file":"lib/Encode/MIME/Name.pm","version":"1.03"},"Encode::Unicode":{"file":"Unicode/Unicode.pm","version":"2.18"},"Encode::CJKConstants":{"file":"lib/Encode/CJKConstants.pm","version":"2.02"},"Encode::Config":{"version":"2.05","file":"lib/Encode/Config.pm"},"encoding":{"version":"2.22","file":"encoding.pm"},"Encode::Unicode::UTF7":{"file":"lib/Encode/Unicode/UTF7.pm","version":"2.10"},"Encode::utf8":{"version":"3.02","file":"Encode.pm"}},"pathname":"D/DA/DANKOGAI/Encode-3.02.tar.gz","version":"3.02","name":"Encode"}