{"name":"Type::Tiny","dist":"Type-Tiny-1.000005","version":"1.000005","target":"Type::Tiny","provides":{"Type::Tiny":{"file":"lib/Type/Tiny.pm","version":"1.000005"},"Types::Standard::Tuple":{"version":"1.000005","file":"lib/Types/Standard/Tuple.pm"},"Type::Parser":{"file":"lib/Type/Parser.pm","version":"1.000005"},"Error::TypeTiny":{"file":"lib/Error/TypeTiny.pm","version":"1.000005"},"Types::Standard::Dict":{"file":"lib/Types/Standard/Dict.pm","version":"1.000005"},"Error::TypeTiny::Compilation":{"version":"1.000005","file":"lib/Error/TypeTiny/Compilation.pm"},"Type::Tiny::Role":{"version":"1.000005","file":"lib/Type/Tiny/Role.pm"},"Type::Coercion::Union":{"version":"1.000005","file":"lib/Type/Coercion/Union.pm"},"Type::Registry":{"version":"1.000005","file":"lib/Type/Registry.pm"},"Type::Coercion::FromMoose":{"version":"1.000005","file":"lib/Type/Coercion/FromMoose.pm"},"Type::Utils":{"file":"lib/Type/Utils.pm","version":"1.000005"},"Types::Standard::Map":{"version":"1.000005","file":"lib/Types/Standard/Map.pm"},"Types::TypeTiny":{"version":"1.000005","file":"lib/Types/TypeTiny.pm"},"Types::Common::String":{"version":"1.000005","file":"lib/Types/Common/String.pm"},"Type::Tiny::_HalfOp":{"file":null,"version":null},"Type::Tiny::Intersection":{"file":"lib/Type/Tiny/Intersection.pm","version":"1.000005"},"Types::Standard":{"version":"1.000005","file":"lib/Types/Standard.pm"},"Type::Coercion":{"version":"1.000005","file":"lib/Type/Coercion.pm"},"Devel::TypeTiny::Perl58Compat":{"version":"1.000005","file":"lib/Devel/TypeTiny/Perl58Compat.pm"},"Error::TypeTiny::WrongNumberOfParameters":{"file":"lib/Error/TypeTiny/WrongNumberOfParameters.pm","version":"1.000005"},"Types::Standard::ScalarRef":{"file":"lib/Types/Standard/ScalarRef.pm","version":"1.000005"},"Type::Tiny::Enum":{"file":"lib/Type/Tiny/Enum.pm","version":"1.000005"},"Type::Tiny::Class":{"file":"lib/Type/Tiny/Class.pm","version":"1.000005"},"Type::Params":{"version":"1.000005","file":"lib/Type/Params.pm"},"Test::TypeTiny":{"file":"lib/Test/TypeTiny.pm","version":"1.000005"},"Reply::Plugin::TypeTiny":{"version":"1.000005","file":"lib/Reply/Plugin/TypeTiny.pm"},"Type::Tiny::Union":{"file":"lib/Type/Tiny/Union.pm","version":"1.000005"},"Types::Standard::HashRef":{"file":"lib/Types/Standard/HashRef.pm","version":"1.000005"},"Type::Library":{"version":"1.000005","file":"lib/Type/Library.pm"},"Types::Common::Numeric":{"file":"lib/Types/Common/Numeric.pm","version":"1.000005"},"Eval::TypeTiny":{"version":"1.000005","file":"lib/Eval/TypeTiny.pm"},"Type::Tiny::Duck":{"version":"1.000005","file":"lib/Type/Tiny/Duck.pm"},"Types::Standard::ArrayRef":{"version":"1.000005","file":"lib/Types/Standard/ArrayRef.pm"},"Error::TypeTiny::Assertion":{"file":"lib/Error/TypeTiny/Assertion.pm","version":"1.000005"},"Devel::TypeTiny::Perl56Compat":{"version":"1.000005","file":"lib/Devel/TypeTiny/Perl56Compat.pm"}},"pathname":"T/TO/TOBYINK/Type-Tiny-1.000005.tar.gz"}