{"dist":"URI-5.05","version":"5.05","provides":{"URI":{"version":"5.05","file":"lib/URI.pm"},"URI::IRI":{"version":"5.05","file":"lib/URI/IRI.pm"},"URI::Escape":{"file":"lib/URI/Escape.pm","version":"5.05"},"URI::gopher":{"file":"lib/URI/gopher.pm","version":"5.05"},"URI::ldap":{"file":"lib/URI/ldap.pm","version":"5.05"},"URI::tn3270":{"version":"5.05","file":"lib/URI/tn3270.pm"},"URI::file::Base":{"version":"5.05","file":"lib/URI/file/Base.pm"},"URI::rsync":{"file":"lib/URI/rsync.pm","version":"5.05"},"URI::pop":{"file":"lib/URI/pop.pm","version":"5.05"},"URI::news":{"version":"5.05","file":"lib/URI/news.pm"},"URI::urn::isbn":{"file":"lib/URI/urn/isbn.pm","version":"5.05"},"URI::file::Mac":{"file":"lib/URI/file/Mac.pm","version":"5.05"},"URI::rlogin":{"file":"lib/URI/rlogin.pm","version":"5.05"},"URI::QueryParam":{"file":"lib/URI/QueryParam.pm","version":"5.05"},"URI::file::Unix":{"version":"5.05","file":"lib/URI/file/Unix.pm"},"URI::ftp":{"version":"5.05","file":"lib/URI/ftp.pm"},"URI::ldapi":{"file":"lib/URI/ldapi.pm","version":"5.05"},"URI::sip":{"version":"5.05","file":"lib/URI/sip.pm"},"URI::ldaps":{"version":"5.05","file":"lib/URI/ldaps.pm"},"URI::mailto":{"version":"5.05","file":"lib/URI/mailto.pm"},"URI::rtsp":{"file":"lib/URI/rtsp.pm","version":"5.05"},"URI::sftp":{"file":"lib/URI/sftp.pm","version":"5.05"},"URI::telnet":{"file":"lib/URI/telnet.pm","version":"5.05"},"URI::http":{"file":"lib/URI/http.pm","version":"5.05"},"URI::ssh":{"version":"5.05","file":"lib/URI/ssh.pm"},"URI::file::FAT":{"version":"5.05","file":"lib/URI/file/FAT.pm"},"URI::file::OS2":{"file":"lib/URI/file/OS2.pm","version":"5.05"},"URI::snews":{"file":"lib/URI/snews.pm","version":"5.05"},"URI::rtspu":{"file":"lib/URI/rtspu.pm","version":"5.05"},"URI::WithBase":{"version":"5.05","file":"lib/URI/WithBase.pm"},"URI::file":{"version":"5.05","file":"lib/URI/file.pm"},"URI::urn::oid":{"version":"5.05","file":"lib/URI/urn/oid.pm"},"URI::Split":{"file":"lib/URI/Split.pm","version":"5.05"},"URI::file::Win32":{"version":"5.05","file":"lib/URI/file/Win32.pm"},"URI::Heuristic":{"file":"lib/URI/Heuristic.pm","version":"5.05"},"URI::mms":{"version":"5.05","file":"lib/URI/mms.pm"},"URI::data":{"version":"5.05","file":"lib/URI/data.pm"},"URI::sips":{"file":"lib/URI/sips.pm","version":"5.05"},"URI::nntp":{"file":"lib/URI/nntp.pm","version":"5.05"},"URI::https":{"file":"lib/URI/https.pm","version":"5.05"},"URI::urn":{"version":"5.05","file":"lib/URI/urn.pm"},"URI::URL":{"version":"5.05","file":"lib/URI/URL.pm"},"URI::file::QNX":{"version":"5.05","file":"lib/URI/file/QNX.pm"}},"name":"URI","target":"URI::URL","pathname":"O/OA/OALDERS/URI-5.05.tar.gz"}