{"version":"2.111","pathname":"D/DS/DSKOLL/IO-stringy-2.111.tar.gz","dist":"IO-stringy-2.111","provides":{"IO::Lines":{"version":"2.111","file":"lib/IO/Lines.pm"},"IO::Scalar":{"version":"2.111","file":"lib/IO/Scalar.pm"},"IO::Stringy":{"version":"2.111","file":"lib/IO/Stringy.pm"},"IO::Wrap":{"version":"2.111","file":"lib/IO/Wrap.pm"},"IO::WrapTie::Master":{"version":"2.111","file":"lib/IO/WrapTie.pm"},"IO::ScalarArray":{"version":"2.111","file":"lib/IO/ScalarArray.pm"},"IO::AtomicFile":{"version":"2.111","file":"lib/IO/AtomicFile.pm"},"IO::WrapTie":{"file":"lib/IO/WrapTie.pm","version":"2.111"},"IO::WrapTie::Slave":{"version":"2.111","file":"lib/IO/WrapTie.pm"},"IO::Clever":{"file":"contrib/Clever.pm","version":"1.01"},"IO::InnerFile":{"file":"lib/IO/InnerFile.pm","version":"2.111"}},"target":"IO::Scalar","name":"IO::Stringy"}