{"name":"Params::ValidationCompiler","dist":"Params-ValidationCompiler-0.27","provides":{"Params::ValidationCompiler::Exceptions":{"version":"0.27","file":"lib/Params/ValidationCompiler/Exceptions.pm"},"Params::ValidationCompiler::Compiler":{"file":"lib/Params/ValidationCompiler/Compiler.pm","version":"0.27"},"Params::ValidationCompiler":{"file":"lib/Params/ValidationCompiler.pm","version":"0.27"}},"target":"Params::ValidationCompiler","pathname":"D/DR/DROLSKY/Params-ValidationCompiler-0.27.tar.gz","version":"0.27"}