{"pathname":"D/DR/DROLSKY/Specio-0.45.tar.gz","name":"Specio","target":"Specio","provides":{"Specio::Declare":{"version":"0.45","file":"lib/Specio/Declare.pm"},"Specio::Subs":{"file":"lib/Specio/Subs.pm","version":"0.45"},"Specio::Exporter":{"version":"0.45","file":"lib/Specio/Exporter.pm"},"Specio::Constraint::AnyIsa":{"file":"lib/Specio/Constraint/AnyIsa.pm","version":"0.45"},"Specio::Constraint::Role::DoesType":{"file":"lib/Specio/Constraint/Role/DoesType.pm","version":"0.45"},"Specio::Registry":{"version":"0.45","file":"lib/Specio/Registry.pm"},"Specio::Library::Builtins":{"version":"0.45","file":"lib/Specio/Library/Builtins.pm"},"Specio::Constraint::AnyCan":{"version":"0.45","file":"lib/Specio/Constraint/AnyCan.pm"},"Specio::Library::Perl":{"version":"0.45","file":"lib/Specio/Library/Perl.pm"},"Specio::Exception":{"version":"0.45","file":"lib/Specio/Exception.pm"},"Specio::Constraint::Role::CanType":{"version":"0.45","file":"lib/Specio/Constraint/Role/CanType.pm"},"Specio::OO":{"version":"0.45","file":"lib/Specio/OO.pm"},"Specio::Coercion":{"version":"0.45","file":"lib/Specio/Coercion.pm"},"Specio":{"file":"lib/Specio.pm","version":"0.45"},"Specio::Constraint::Role::IsaType":{"file":"lib/Specio/Constraint/Role/IsaType.pm","version":"0.45"},"Specio::DeclaredAt":{"version":"0.45","file":"lib/Specio/DeclaredAt.pm"},"Specio::Library::Numeric":{"version":"0.45","file":"lib/Specio/Library/Numeric.pm"},"Specio::Library::Structured":{"file":"lib/Specio/Library/Structured.pm","version":"0.45"},"Specio::Constraint::Intersection":{"version":"0.45","file":"lib/Specio/Constraint/Intersection.pm"},"Test::Specio":{"file":"lib/Test/Specio.pm","version":"0.45"},"Specio::Helpers":{"version":"0.45","file":"lib/Specio/Helpers.pm"},"Specio::Constraint::Parameterized":{"file":"lib/Specio/Constraint/Parameterized.pm","version":"0.45"},"Specio::PartialDump":{"version":"0.45","file":"lib/Specio/PartialDump.pm"},"Specio::Role::Inlinable":{"version":"0.45","file":"lib/Specio/Role/Inlinable.pm"},"Specio::Library::String":{"version":"0.45","file":"lib/Specio/Library/String.pm"},"Specio::Constraint::Structured":{"version":"0.45","file":"lib/Specio/Constraint/Structured.pm"},"Specio::TypeChecks":{"version":"0.45","file":"lib/Specio/TypeChecks.pm"},"Specio::Library::Structured::Tuple":{"file":"lib/Specio/Library/Structured/Tuple.pm","version":"0.45"},"Specio::Constraint::Role::Interface":{"version":"0.45","file":"lib/Specio/Constraint/Role/Interface.pm"},"Specio::Constraint::Union":{"version":"0.45","file":"lib/Specio/Constraint/Union.pm"},"Specio::Constraint::ObjectCan":{"version":"0.45","file":"lib/Specio/Constraint/ObjectCan.pm"},"Specio::Library::Structured::Dict":{"version":"0.45","file":"lib/Specio/Library/Structured/Dict.pm"},"Specio::Constraint::Parameterizable":{"file":"lib/Specio/Constraint/Parameterizable.pm","version":"0.45"},"Specio::Constraint::Enum":{"version":"0.45","file":"lib/Specio/Constraint/Enum.pm"},"Specio::Constraint::Simple":{"version":"0.45","file":"lib/Specio/Constraint/Simple.pm"},"Specio::Constraint::Structurable":{"file":"lib/Specio/Constraint/Structurable.pm","version":"0.45"},"Specio::Constraint::ObjectIsa":{"version":"0.45","file":"lib/Specio/Constraint/ObjectIsa.pm"},"Specio::Library::Structured::Map":{"version":"0.45","file":"lib/Specio/Library/Structured/Map.pm"},"Specio::Constraint::AnyDoes":{"file":"lib/Specio/Constraint/AnyDoes.pm","version":"0.45"},"Specio::Constraint::ObjectDoes":{"file":"lib/Specio/Constraint/ObjectDoes.pm","version":"0.45"}},"version":"0.45","dist":"Specio-0.45"}