{"version":"1.215","target":"PPI::Document","pathname":"A/AD/ADAMK/PPI-1.215.tar.gz","name":"PPI","provides":{"PPI::Statement::Break":{"file":"lib/PPI/Statement/Break.pm","version":"1.215"},"PPI::Transform::UpdateCopyright":{"version":"1.215","file":"lib/PPI/Transform/UpdateCopyright.pm"},"PPI::Token::Number::Binary":{"version":"1.215","file":"lib/PPI/Token/Number/Binary.pm"},"PPI::Token::_QuoteEngine":{"version":"1.215","file":"lib/PPI/Token/_QuoteEngine.pm"},"PPI::Token::ArrayIndex":{"version":"1.215","file":"lib/PPI/Token/ArrayIndex.pm"},"PPI::Token::Quote::Double":{"file":"lib/PPI/Token/Quote/Double.pm","version":"1.215"},"PPI::Util":{"version":"1.215","file":"lib/PPI/Util.pm"},"PPI::Lexer":{"file":"lib/PPI/Lexer.pm","version":"1.215"},"PPI::Structure::Given":{"version":"1.215","file":"lib/PPI/Structure/Given.pm"},"PPI::Token::Prototype":{"version":"1.215","file":"lib/PPI/Token/Prototype.pm"},"PPI::Structure::Unknown":{"version":"1.215","file":"lib/PPI/Structure/Unknown.pm"},"PPI::Token::Regexp::Substitute":{"version":"1.215","file":"lib/PPI/Token/Regexp/Substitute.pm"},"PPI::Token::Number::Octal":{"file":"lib/PPI/Token/Number/Octal.pm","version":"1.215"},"PPI::Statement::Sub":{"file":"lib/PPI/Statement/Sub.pm","version":"1.215"},"PPI::Statement::Unknown":{"file":"lib/PPI/Statement/Unknown.pm","version":"1.215"},"PPI::Token::Comment":{"file":"lib/PPI/Token/Comment.pm","version":"1.215"},"PPI::Statement::Given":{"version":"1.215","file":"lib/PPI/Statement/Given.pm"},"PPI::Token::Word":{"version":"1.215","file":"lib/PPI/Token/Word.pm"},"PPI::Token::Number::Version":{"version":"1.215","file":"lib/PPI/Token/Number/Version.pm"},"PPI::Token::QuoteLike::Readline":{"version":"1.215","file":"lib/PPI/Token/QuoteLike/Readline.pm"},"PPI::Token::Magic":{"version":"1.215","file":"lib/PPI/Token/Magic.pm"},"PPI::Structure::Block":{"file":"lib/PPI/Structure/Block.pm","version":"1.215"},"PPI::Structure::Condition":{"version":"1.215","file":"lib/PPI/Structure/Condition.pm"},"PPI::Find":{"file":"lib/PPI/Find.pm","version":"1.215"},"PPI::Token":{"version":"1.215","file":"lib/PPI/Token.pm"},"PPI::Token::Number::Exp":{"file":"lib/PPI/Token/Number/Exp.pm","version":"1.215"},"PPI::Token::Number::Hex":{"file":"lib/PPI/Token/Number/Hex.pm","version":"1.215"},"PPI::Token::Data":{"file":"lib/PPI/Token/Data.pm","version":"1.215"},"PPI::Token::_QuoteEngine::Simple":{"version":"1.215","file":"lib/PPI/Token/_QuoteEngine/Simple.pm"},"PPI::Document::Normalized":{"version":"1.215","file":"lib/PPI/Document/Normalized.pm"},"PPI::Token::Regexp":{"file":"lib/PPI/Token/Regexp.pm","version":"1.215"},"PPI::Structure::For":{"version":"1.215","file":"lib/PPI/Structure/For.pm"},"PPI::Token::QuoteLike::Words":{"file":"lib/PPI/Token/QuoteLike/Words.pm","version":"1.215"},"PPI::Statement::Include::Perl6":{"file":"lib/PPI/Statement/Include/Perl6.pm","version":"1.215"},"PPI::Structure":{"version":"1.215","file":"lib/PPI/Structure.pm"},"PPI::Token::Quote":{"file":"lib/PPI/Token/Quote.pm","version":"1.215"},"PPI::Statement::Null":{"version":"1.215","file":"lib/PPI/Statement/Null.pm"},"PPI::Token::Number":{"file":"lib/PPI/Token/Number.pm","version":"1.215"},"PPI::Document":{"version":"1.215","file":"lib/PPI/Document.pm"},"PPI::Statement::Package":{"version":"1.215","file":"lib/PPI/Statement/Package.pm"},"PPI::Statement::Data":{"file":"lib/PPI/Statement/Data.pm","version":"1.215"},"PPI::Structure::When":{"version":"1.215","file":"lib/PPI/Structure/When.pm"},"PPI::Dumper":{"version":"1.215","file":"lib/PPI/Dumper.pm"},"PPI::Token::Label":{"version":"1.215","file":"lib/PPI/Token/Label.pm"},"PPI::Token::Number::Float":{"file":"lib/PPI/Token/Number/Float.pm","version":"1.215"},"PPI::Cache":{"file":"lib/PPI/Cache.pm","version":"1.215"},"PPI":{"file":"lib/PPI.pm","version":"1.215"},"PPI::Structure::Subscript":{"version":"1.215","file":"lib/PPI/Structure/Subscript.pm"},"PPI::Token::HereDoc":{"version":"1.215","file":"lib/PPI/Token/HereDoc.pm"},"PPI::Token::Operator":{"file":"lib/PPI/Token/Operator.pm","version":"1.215"},"PPI::Token::BOM":{"file":"lib/PPI/Token/BOM.pm","version":"1.215"},"PPI::Token::QuoteLike::Backtick":{"file":"lib/PPI/Token/QuoteLike/Backtick.pm","version":"1.215"},"PPI::Document::File":{"version":"1.215","file":"lib/PPI/Document/File.pm"},"PPI::Token::Symbol":{"file":"lib/PPI/Token/Symbol.pm","version":"1.215"},"PPI::Tokenizer":{"file":"lib/PPI/Tokenizer.pm","version":"1.215"},"PPI::Token::Unknown":{"version":"1.215","file":"lib/PPI/Token/Unknown.pm"},"PPI::Token::End":{"version":"1.215","file":"lib/PPI/Token/End.pm"},"PPI::Token::Quote::Single":{"version":"1.215","file":"lib/PPI/Token/Quote/Single.pm"},"PPI::Token::Attribute":{"version":"1.215","file":"lib/PPI/Token/Attribute.pm"},"PPI::Statement::Expression":{"file":"lib/PPI/Statement/Expression.pm","version":"1.215"},"PPI::Token::DashedWord":{"version":"1.215","file":"lib/PPI/Token/DashedWord.pm"},"PPI::Statement::End":{"version":"1.215","file":"lib/PPI/Statement/End.pm"},"PPI::Token::Pod":{"file":"lib/PPI/Token/Pod.pm","version":"1.215"},"PPI::Token::QuoteLike::Command":{"file":"lib/PPI/Token/QuoteLike/Command.pm","version":"1.215"},"PPI::Normal::Standard":{"version":"1.215","file":"lib/PPI/Normal/Standard.pm"},"PPI::Statement::Scheduled":{"file":"lib/PPI/Statement/Scheduled.pm","version":"1.215"},"PPI::Token::Structure":{"file":"lib/PPI/Token/Structure.pm","version":"1.215"},"PPI::Token::Whitespace":{"file":"lib/PPI/Token/Whitespace.pm","version":"1.215"},"PPI::Token::Separator":{"version":"1.215","file":"lib/PPI/Token/Separator.pm"},"PPI::XSAccessor":{"version":"1.215","file":"lib/PPI/XSAccessor.pm"},"PPI::Exception::ParserRejection":{"version":"1.215","file":"lib/PPI/Exception/ParserRejection.pm"},"PPI::Statement::Compound":{"file":"lib/PPI/Statement/Compound.pm","version":"1.215"},"PPI::Token::Cast":{"version":"1.215","file":"lib/PPI/Token/Cast.pm"},"PPI::Node":{"file":"lib/PPI/Node.pm","version":"1.215"},"PPI::Statement::Include":{"file":"lib/PPI/Statement/Include.pm","version":"1.215"},"PPI::Structure::List":{"version":"1.215","file":"lib/PPI/Structure/List.pm"},"PPI::Token::Quote::Literal":{"version":"1.215","file":"lib/PPI/Token/Quote/Literal.pm"},"PPI::Token::_QuoteEngine::Full":{"file":"lib/PPI/Token/_QuoteEngine/Full.pm","version":"1.215"},"PPI::Statement::When":{"file":"lib/PPI/Statement/When.pm","version":"1.215"},"PPI::Transform":{"version":"1.215","file":"lib/PPI/Transform.pm"},"PPI::Element":{"version":"1.215","file":"lib/PPI/Element.pm"},"PPI::Exception::ParserTimeout":{"file":"lib/PPI/Exception/ParserTimeout.pm","version":"1.215"},"PPI::Token::Regexp::Match":{"file":"lib/PPI/Token/Regexp/Match.pm","version":"1.215"},"PPI::Statement::UnmatchedBrace":{"file":"lib/PPI/Statement/UnmatchedBrace.pm","version":"1.215"},"PPI::Token::QuoteLike":{"version":"1.215","file":"lib/PPI/Token/QuoteLike.pm"},"PPI::Exception":{"version":"1.215","file":"lib/PPI/Exception.pm"},"PPI::Document::Fragment":{"file":"lib/PPI/Document/Fragment.pm","version":"1.215"},"PPI::Token::Regexp::Transliterate":{"version":"1.215","file":"lib/PPI/Token/Regexp/Transliterate.pm"},"PPI::Statement":{"file":"lib/PPI/Statement.pm","version":"1.215"},"PPI::Statement::Variable":{"file":"lib/PPI/Statement/Variable.pm","version":"1.215"},"PPI::Token::Quote::Interpolate":{"version":"1.215","file":"lib/PPI/Token/Quote/Interpolate.pm"},"PPI::Normal":{"file":"lib/PPI/Normal.pm","version":"1.215"},"PPI::Token::QuoteLike::Regexp":{"version":"1.215","file":"lib/PPI/Token/QuoteLike/Regexp.pm"},"PPI::Structure::Constructor":{"file":"lib/PPI/Structure/Constructor.pm","version":"1.215"}},"dist":"PPI-1.215"}