{"dist":"Lingua-Stem-2.31","pathname":"S/SN/SNOWHARE/Lingua-Stem-2.31.tar.gz","provides":{"Lingua::Stem::En":{"file":"lib/Lingua/Stem/En.pm","version":"2.31"},"Lingua::Stem":{"file":"lib/Lingua/Stem.pm","version":"2.31"},"Lingua::Stem::Gl":{"version":"2.31","file":"lib/Lingua/Stem/Gl.pm"},"Lingua::Stem::EnBroken":{"version":"2.31","file":"lib/Lingua/Stem/EnBroken.pm"},"Lingua::Stem::Da":{"version":"2.31","file":"lib/Lingua/Stem/Da.pm"},"Lingua::Stem::AutoLoader":{"file":"lib/Lingua/Stem/AutoLoader.pm","version":"2.31"},"Lingua::Stem::Pt":{"file":"lib/Lingua/Stem/Pt.pm","version":"2.31"},"Lingua::Stem::No":{"version":"2.31","file":"lib/Lingua/Stem/No.pm"},"Lingua::Stem::De":{"version":"2.31","file":"lib/Lingua/Stem/De.pm"},"Lingua::Stem::Sv":{"file":"lib/Lingua/Stem/Sv.pm","version":"2.31"}},"version":"2.31","target":"Lingua::Stem","name":"Lingua::Stem"}