{"pathname":"D/DA/DAGOLDEN/CPAN-Meta-2.150005.tar.gz","target":"CPAN::Meta","dist":"CPAN-Meta-2.150005","version":"2.150005","name":"CPAN::Meta","provides":{"CPAN::Meta::History":{"file":"lib/CPAN/Meta/History.pm","version":"2.150005"},"CPAN::Meta":{"file":"lib/CPAN/Meta.pm","version":"2.150005"},"CPAN::Meta::Merge":{"version":"2.150005","file":"lib/CPAN/Meta/Merge.pm"},"CPAN::Meta::Prereqs":{"version":"2.150005","file":"lib/CPAN/Meta/Prereqs.pm"},"CPAN::Meta::Validator":{"version":"2.150005","file":"lib/CPAN/Meta/Validator.pm"},"CPAN::Meta::Converter":{"file":"lib/CPAN/Meta/Converter.pm","version":"2.150005"},"CPAN::Meta::Feature":{"file":"lib/CPAN/Meta/Feature.pm","version":"2.150005"},"CPAN::Meta::Spec":{"file":"lib/CPAN/Meta/Spec.pm","version":"2.150005"}}}