{"provides":{"URI::ldaps":{"file":"lib/URI/ldaps.pm","version":"1.71"},"URI":{"version":"1.71","file":"lib/URI.pm"},"URI::file":{"file":"lib/URI/file.pm","version":"4.21"},"URI::_login":{"file":"lib/URI/_login.pm","version":"1.71"},"URI::mms":{"file":"lib/URI/mms.pm","version":"1.71"},"URI::_userpass":{"file":"lib/URI/_userpass.pm","version":"1.71"},"URI::rlogin":{"file":"lib/URI/rlogin.pm","version":"1.71"},"URI::Split":{"version":"1.71","file":"lib/URI/Split.pm"},"URI::ssh":{"file":"lib/URI/ssh.pm","version":"1.71"},"URI::telnet":{"version":"1.71","file":"lib/URI/telnet.pm"},"URI::_segment":{"version":"1.71","file":"lib/URI/_segment.pm"},"URI::urn::oid":{"version":"1.71","file":"lib/URI/urn/oid.pm"},"URI::rsync":{"file":"lib/URI/rsync.pm","version":"1.71"},"URI::file::FAT":{"version":"1.71","file":"lib/URI/file/FAT.pm"},"URI::http":{"version":"1.71","file":"lib/URI/http.pm"},"URI::IRI":{"version":"1.71","file":"lib/URI/IRI.pm"},"URI::_generic":{"version":"1.71","file":"lib/URI/_generic.pm"},"URI::URL":{"file":"lib/URI/URL.pm","version":"5.04"},"URI::file::Mac":{"file":"lib/URI/file/Mac.pm","version":"1.71"},"URI::urn":{"version":"1.71","file":"lib/URI/urn.pm"},"URI::nntp":{"version":"1.71","file":"lib/URI/nntp.pm"},"URI::_punycode":{"file":"lib/URI/_punycode.pm","version":"1.71"},"URI::ldapi":{"file":"lib/URI/ldapi.pm","version":"1.71"},"URI::sftp":{"file":"lib/URI/sftp.pm","version":"1.71"},"URI::mailto":{"file":"lib/URI/mailto.pm","version":"1.71"},"URI::sips":{"version":"1.71","file":"lib/URI/sips.pm"},"URI::snews":{"file":"lib/URI/snews.pm","version":"1.71"},"URI::rtspu":{"version":"1.71","file":"lib/URI/rtspu.pm"},"URI::sip":{"file":"lib/URI/sip.pm","version":"1.71"},"URI::_foreign":{"version":"1.71","file":"lib/URI/_foreign.pm"},"URI::urn::isbn":{"file":"lib/URI/urn/isbn.pm"},"URI::data":{"version":"1.71","file":"lib/URI/data.pm"},"URI::tn3270":{"version":"1.71","file":"lib/URI/tn3270.pm"},"URI::_ldap":{"version":"1.71","file":"lib/URI/_ldap.pm"},"URI::file::QNX":{"version":"1.71","file":"lib/URI/file/QNX.pm"},"URI::file::OS2":{"version":"1.71","file":"lib/URI/file/OS2.pm"},"URI::file::Base":{"file":"lib/URI/file/Base.pm","version":"1.71"},"URI::_query":{"version":"1.71","file":"lib/URI/_query.pm"},"URI::_idna":{"version":"1.71","file":"lib/URI/_idna.pm"},"URI::WithBase":{"file":"lib/URI/WithBase.pm","version":"2.20"},"URI::https":{"version":"1.71","file":"lib/URI/https.pm"},"URI::file::Unix":{"file":"lib/URI/file/Unix.pm","version":"1.71"},"URI::pop":{"version":"1.71","file":"lib/URI/pop.pm"},"URI::ftp":{"version":"1.71","file":"lib/URI/ftp.pm"},"URI::QueryParam":{"file":"lib/URI/QueryParam.pm","version":"1.71"},"URI::gopher":{"version":"1.71","file":"lib/URI/gopher.pm"},"URI::Heuristic":{"version":"4.20","file":"lib/URI/Heuristic.pm"},"URI::_server":{"file":"lib/URI/_server.pm","version":"1.71"},"URI::Escape":{"file":"lib/URI/Escape.pm","version":"3.31"},"URI::ldap":{"file":"lib/URI/ldap.pm","version":"1.71"},"URI::file::Win32":{"file":"lib/URI/file/Win32.pm","version":"1.71"},"URI::rtsp":{"file":"lib/URI/rtsp.pm","version":"1.71"},"URI::news":{"version":"1.71","file":"lib/URI/news.pm"}},"name":"URI","target":"URI","pathname":"E/ET/ETHER/URI-1.71.tar.gz","version":"1.71","dist":"URI-1.71"}