{"target":"LWP::UserAgent","name":"libwww::perl","version":"6.49","provides":{"LWP::Protocol::file":{"version":"6.49","file":"lib/LWP/Protocol/file.pm"},"LWP::Simple":{"file":"lib/LWP/Simple.pm","version":"6.49"},"LWP::Authen::Ntlm":{"file":"lib/LWP/Authen/Ntlm.pm","version":"6.49"},"LWP::Debug":{"version":"6.49","x_deprecated":1,"file":"lib/LWP/Debug.pm"},"LWP::Protocol::nntp":{"version":"6.49","file":"lib/LWP/Protocol/nntp.pm"},"LWP::DebugFile":{"version":"6.49","file":"lib/LWP/DebugFile.pm"},"LWP::Debug::TraceHTTP":{"file":"lib/LWP/Debug/TraceHTTP.pm","version":"6.49"},"LWP::Protocol::loopback":{"file":"lib/LWP/Protocol/loopback.pm","version":"6.49"},"LWP::Protocol::nogo":{"file":"lib/LWP/Protocol/nogo.pm","version":"6.49"},"LWP::Protocol::cpan":{"version":"6.49","file":"lib/LWP/Protocol/cpan.pm"},"LWP::Authen::Digest":{"file":"lib/LWP/Authen/Digest.pm","version":"6.49"},"LWP::Protocol::ftp":{"version":"6.49","file":"lib/LWP/Protocol/ftp.pm"},"LWP::MemberMixin":{"version":"6.49","file":"lib/LWP/MemberMixin.pm"},"LWP::Protocol::mailto":{"version":"6.49","file":"lib/LWP/Protocol/mailto.pm"},"LWP::Protocol":{"file":"lib/LWP/Protocol.pm","version":"6.49"},"LWP::Protocol::data":{"file":"lib/LWP/Protocol/data.pm","version":"6.49"},"LWP::ConnCache":{"file":"lib/LWP/ConnCache.pm","version":"6.49"},"LWP::RobotUA":{"file":"lib/LWP/RobotUA.pm","version":"6.49"},"LWP":{"file":"lib/LWP.pm","version":"6.49"},"LWP::UserAgent":{"version":"6.49","file":"lib/LWP/UserAgent.pm"},"LWP::Protocol::http":{"file":"lib/LWP/Protocol/http.pm","version":"6.49"},"LWP::Authen::Basic":{"file":"lib/LWP/Authen/Basic.pm","version":"6.49"},"LWP::Protocol::gopher":{"file":"lib/LWP/Protocol/gopher.pm","version":"6.49"}},"pathname":"O/OA/OALDERS/libwww-perl-6.49.tar.gz","dist":"libwww-perl-6.49"}