{"pathname":"D/DR/DROLSKY/DateTime-Locale-1.31.tar.gz","dist":"DateTime-Locale-1.31","version":"1.31","name":"DateTime::Locale","provides":{"DateTime::Locale::Data":{"version":"1.31","file":"lib/DateTime/Locale/Data.pm"},"DateTime::Locale::Catalog":{"file":"lib/DateTime/Locale/Catalog.pm","version":"1.31"},"DateTime::Locale":{"file":"lib/DateTime/Locale.pm","version":"1.31"},"DateTime::Locale::FromData":{"file":"lib/DateTime/Locale/FromData.pm","version":"1.31"},"DateTime::Locale::Util":{"version":"1.31","file":"lib/DateTime/Locale/Util.pm"},"DateTime::Locale::Base":{"file":"lib/DateTime/Locale/Base.pm","version":"1.31"}},"target":"DateTime::Locale"}