{"pathname":"D/DR/DROLSKY/DateTime-1.50.tar.gz","provides":{"DateTime::Infinite":{"version":"1.50","file":"lib/DateTime/Infinite.pm"},"DateTime::PPExtra":{"file":"lib/DateTime/PPExtra.pm","version":"1.50"},"DateTime::Helpers":{"file":"lib/DateTime/Helpers.pm","version":"1.50"},"DateTime::Infinite::Future":{"file":"lib/DateTime/Infinite.pm","version":"1.50"},"DateTime::Infinite::Past":{"file":"lib/DateTime/Infinite.pm","version":"1.50"},"DateTime::Types":{"file":"lib/DateTime/Types.pm","version":"1.50"},"DateTime::Duration":{"file":"lib/DateTime/Duration.pm","version":"1.50"},"DateTime::LeapSecond":{"file":"lib/DateTime/LeapSecond.pm","version":"1.50"},"DateTime":{"version":"1.50","file":"lib/DateTime.pm"},"DateTime::PP":{"file":"lib/DateTime/PP.pm","version":"1.50"}},"name":"DateTime","target":"DateTime","version":"1.50","dist":"DateTime-1.50"}