{"dist":"Params-ValidationCompiler-0.30","pathname":"D/DR/DROLSKY/Params-ValidationCompiler-0.30.tar.gz","name":"Params::ValidationCompiler","target":"Params::ValidationCompiler","provides":{"Params::ValidationCompiler":{"version":"0.30","file":"lib/Params/ValidationCompiler.pm"},"Params::ValidationCompiler::Compiler":{"file":"lib/Params/ValidationCompiler/Compiler.pm","version":"0.30"},"Params::ValidationCompiler::Exceptions":{"version":"0.30","file":"lib/Params/ValidationCompiler/Exceptions.pm"}},"version":"0.30"}