{"name":"MooseX::Getopt","version":"0.74","dist":"MooseX-Getopt-0.74","provides":{"MooseX::Getopt::Meta::Attribute":{"file":"lib/MooseX/Getopt/Meta/Attribute.pm","version":"0.74"},"MooseX::Getopt::Dashes":{"file":"lib/MooseX/Getopt/Dashes.pm","version":"0.74"},"MooseX::Getopt::Meta::Attribute::Trait":{"file":"lib/MooseX/Getopt/Meta/Attribute/Trait.pm","version":"0.74"},"MooseX::Getopt::Meta::Attribute::NoGetopt":{"file":"lib/MooseX/Getopt/Meta/Attribute/NoGetopt.pm","version":"0.74"},"MooseX::Getopt":{"file":"lib/MooseX/Getopt.pm","version":"0.74"},"MooseX::Getopt::GLD":{"file":"lib/MooseX/Getopt/GLD.pm","version":"0.74"},"MooseX::Getopt::Strict":{"file":"lib/MooseX/Getopt/Strict.pm","version":"0.74"},"MooseX::Getopt::OptionTypeMap":{"file":"lib/MooseX/Getopt/OptionTypeMap.pm","version":"0.74"},"MooseX::Getopt::Meta::Attribute::Trait::NoGetopt":{"file":"lib/MooseX/Getopt/Meta/Attribute/Trait/NoGetopt.pm","version":"0.74"},"MooseX::Getopt::Basic":{"version":"0.74","file":"lib/MooseX/Getopt/Basic.pm"},"MooseX::Getopt::ProcessedArgv":{"file":"lib/MooseX/Getopt/ProcessedArgv.pm","version":"0.74"}},"pathname":"E/ET/ETHER/MooseX-Getopt-0.74.tar.gz","target":"MooseX::Getopt"}