{"name":"MooseX::Role::Parameterized","provides":{"MooseX::Role::Parameterized":{"file":"lib/MooseX/Role/Parameterized.pm","version":"1.11"},"MooseX::Role::Parameterized::Meta::Role::Parameterized":{"file":"lib/MooseX/Role/Parameterized/Meta/Role/Parameterized.pm","version":"1.11"},"MooseX::Role::Parameterized::Meta::Trait::Parameterized":{"file":"lib/MooseX/Role/Parameterized/Meta/Trait/Parameterized.pm","version":"1.11"},"MooseX::Role::Parameterised":{"version":"1.11","file":"lib/MooseX/Role/Parameterised.pm"},"MooseX::Role::Parameterized::Parameters":{"version":"1.11","file":"lib/MooseX/Role/Parameterized/Parameters.pm"},"MooseX::Role::Parameterized::Meta::Trait::Parameterizable":{"version":"1.11","file":"lib/MooseX/Role/Parameterized/Meta/Trait/Parameterizable.pm"}},"dist":"MooseX-Role-Parameterized-1.11","version":"1.11","pathname":"E/ET/ETHER/MooseX-Role-Parameterized-1.11.tar.gz","target":"MooseX::Role::Parameterized"}