{"provides":{"IO::Seekable":{"version":"1.10","file":"lib/IO/Seekable.pm"},"IO::Pipe":{"version":"1.13","file":"lib/IO/Pipe.pm"},"IO::File":{"version":"1.14","file":"lib/IO/File.pm"},"IO::Socket::UNIX":{"version":"1.23","file":"lib/IO/Socket/UNIX.pm"},"IO::Socket::INET":{"version":"1.31","file":"lib/IO/Socket/INET.pm"},"IO::Handle":{"version":"1.28","file":"lib/IO/Handle.pm"},"IO::Socket":{"version":"1.31","file":"lib/IO/Socket.pm"},"IO":{"version":"1.25","file":"IO.pm"},"IO::Select":{"version":"1.17","file":"lib/IO/Select.pm"},"IO::Poll":{"version":"0.07","file":"lib/IO/Poll.pm"},"IO::Pipe::End":{"version":"1.13","file":"lib/IO/Pipe.pm"},"IO::Dir":{"version":"1.07","file":"lib/IO/Dir.pm"}},"target":"IO::File","version":"1.25","name":"IO","dist":"IO-1.25","pathname":"G/GB/GBARR/IO-1.25.tar.gz"}